{
  "mode": "pre",
  "tag": "beta",
  "initialVersions": {
    "ai-example": "0.1.1",
    "charts-python-example": "0.1.4",
    "dev-server-example": "0.1.4",
    "sandbox-filesystem-snapshots-example": "0.0.17",
    "install-packages-example": "0.1.4",
    "private-repo-example": "0.1.4",
    "sandbox-basics-example": "0.1.4",
    "workflow-code-runner-example": "0.1.6",
    "@vercel/pty-tunnel": "2.0.3",
    "@vercel/pty-tunnel-server": "0.0.2",
    "sandbox": "2.5.12",
    "@vercel/sandbox": "1.10.2"
  },
  "changesets": [
    "beige-dogs-melt",
    "big-cats-worry",
    "bumpy-keys-try",
    "chilly-ducks-crash",
    "clean-jeans-build",
    "cli-ports-config",
    "cold-falcons-read",
    "cold-pillows-wave",
    "common-corners-leave",
    "cyan-bats-clap",
    "dirty-cows-talk",
    "empty-trains-tie",
    "evil-results-hope",
    "fair-pears-dream",
    "fluffy-ports-update",
    "fresh-auth-retry",
    "fresh-pumas-own",
    "fresh-rings-rescue",
    "funny-areas-boil",
    "giant-dogs-report",
    "legal-rings-work",
    "light-results-change",
    "open-planets-joke",
    "public-ears-heal",
    "sandbox-cp-error-payload",
    "sandbox-fork",
    "seven-olives-mate",
    "slick-colts-learn",
    "some-numbers-arrive",
    "sour-rocks-grin",
    "stale-hotels-grow",
    "tangy-schools-like",
    "tender-experts-cover",
    "tough-roses-vanish",
    "vast-moles-train",
    "wet-goats-jam",
    "whole-berries-juggle"
  ]
}
